AUTHORS.rst
CHANGELOG.rst
CONTRIBUTING.rst
LICENSE
MANIFEST.in
README.rst
setup.cfg
setup.py
apispec/__init__.py
apispec/auto_ref_strategy.py
apispec/compat.py
apispec/core.py
apispec/exceptions.py
apispec/lazy_dict.py
apispec/utils.py
apispec/ext/__init__.py
apispec/ext/bottle.py
apispec/ext/flask.py
apispec/ext/tornado.py
apispec/ext/marshmallow/__init__.py
apispec/ext/marshmallow/swagger.py
docs/Makefile
docs/api_core.rst
docs/api_ext.rst
docs/authors.rst
docs/changelog.rst
docs/conf.py
docs/contributing.rst
docs/ecosystem.rst
docs/index.rst
docs/install.rst
docs/license.rst
docs/make.bat
docs/quickstart.rst
docs/requirements.txt
docs/special_topics.rst
docs/using_plugins.rst
docs/writing_plugins.rst
hapic_apispec.egg-info/PKG-INFO
hapic_apispec.egg-info/SOURCES.txt
hapic_apispec.egg-info/dependency_links.txt
hapic_apispec.egg-info/not-zip-safe
hapic_apispec.egg-info/requires.txt
hapic_apispec.egg-info/top_level.txt
tests/__init__.py
tests/schemas.py
tests/test_auto_ref_strategy.py
tests/test_core.py
tests/test_ext_bottle.py
tests/test_ext_flask.py
tests/test_ext_marshmallow.py
tests/test_ext_order.py
tests/test_ext_tornado.py
tests/test_swagger.py
tests/test_utils.py
tests/plugins/__init__.py
tests/plugins/dummy_plugin.py
tests/plugins/dummy_plugin_no_setup.py