Metadata-Version: 1.1
Name: hapic-apispec
Version: 0.35.0
Summary: A pluggable API specification generator. Currently supports the OpenAPI specification (f.k.a. the Swagger specification).
Home-page: https://github.com/algoo/apispec
Author: Steven Loria, Josh Carp
Author-email: sloria1@gmail.com
License: MIT
Keywords: apispec swagger openapi specification documentation spec rest api
Platform: UNKNOWN
Classifier: Development Status :: 4 - Beta
Classifier: Intended Audience :: Developers
Classifier: License :: OSI Approved :: MIT License
Classifier: Natural Language :: English
Classifier: Programming Language :: Python :: 2
Classifier: Programming Language :: Python :: 2.7
Classifier: Programming Language :: Python :: 3
Classifier: Programming Language :: Python :: 3.4
Classifier: Programming Language :: Python :: 3.5
Classifier: Programming Language :: Python :: 3.6
